Workbook

Sheet Executive Dashboard
A1: LA DIPERIE — FINANCIAL REPORTING DASHBOARD
A2: Fiscal Year 2024–2025 | Two-Location Consolidated | Prepared by Anis Bouchema | Revenue Base: $550K+
B4: Total Revenue | D4: Gross Margin | F4: Net Income | H4: Cash Position | J4: YoY Revenue Growth | L4: Avg Order Value
B5: ='Monthly P&L'!N4 -> 805900 | D5: ='Monthly P&L'!N10 -> 0.68491376 | F5: ='Monthly P&L'!N18 -> 226217 | H5: ='Cash Flow'!N19 -> 263017 | J5: =('Monthly P&L'!N4-'Monthly P&L'!B4)/'Monthly P&L'!B4 -> 16.256959 | L5: ='Monthly P&L'!N4/'KPI Tracker'!N5 -> 9.9987593
A8: VARIANCE ALERTS & PERFORMANCE FLAGS
A9: Metric | B9: Budget | C9: Actual | D9: Variance ($) | E9: Variance (%) | F9: Status | G9: Alert
A10: Revenue | B10: 565000 | C10: ='Monthly P&L'!N4 -> 805900 | D10: =C10-B10 -> 240900 | E10: =IF(B10=0,0,D10/B10) -> 0.42637168 | F10: =IF(E10>0.02,"Favorable",IF(E10<-0.02,"Unfavorable","On Track")) -> Favorable | G10: =IF(ABS(E10)>0.05,"⚠ REVIEW",IF(ABS(E10)>0.02,"△ MONITOR","✓ OK")) -> ⚠ REVIEW
A11: COGS | B11: 197750 | C11: ='Monthly P&L'!N7 -> -253928 | D11: =C11-B11 -> -451678 | E11: =IF(B11=0,0,D11/B11) -> -2.284086 | F11: =IF(E11>0.02,"Favorable",IF(E11<-0.02,"Unfavorable","On Track")) -> Unfavorable | G11: =IF(ABS(E11)>0.05,"⚠ REVIEW",IF(ABS(E11)>0.02,"△ MONITOR","✓ OK")) -> ⚠ REVIEW
A12: Gross Profit | B12: =B10-B11 -> 367250 | C12: ='Monthly P&L'!N8 -> 551972 | D12: =C12-B12 -> 184722 | E12: =IF(B12=0,0,D12/B12) -> 0.50298707 | F12: =IF(E12>0.02,"Favorable",IF(E12<-0.02,"Unfavorable","On Track")) -> Favorable | G12: =IF(ABS(E12)>0.05,"⚠ REVIEW",IF(ABS(E12)>0.02,"△ MONITOR","✓ OK")) -> ⚠ REVIEW
A13: Operating Expenses | B13: 254250 | C13: ='Monthly P&L'!N15 -> -325755 | D13: =C13-B13 -> -580005 | E13: =IF(B13=0,0,D13/B13) -> -2.2812389 | F13: =IF(E13>0.02,"Favorable",IF(E13<-0.02,"Unfavorable","On Track")) -> Unfavorable | G13: =IF(ABS(E13)>0.05,"⚠ REVIEW",IF(ABS(E13)>0.02,"△ MONITOR","✓ OK")) -> ⚠ REVIEW
A14: Net Income | B14: =B12-B13 -> 113000 | C14: ='Monthly P&L'!N18 -> 226217 | D14: =C14-B14 -> 113217 | E14: =IF(B14=0,0,D14/B14) -> 1.0019204 | F14: =IF(E14>0.02,"Favorable",IF(E14<-0.02,"Unfavorable","On Track")) -> Favorable | G14: =IF(ABS(E14)>0.05,"⚠ REVIEW",IF(ABS(E14)>0.02,"△ MONITOR","✓ OK")) -> ⚠ REVIEW
A16: MONTHLY REVENUE TREND — CONSOLIDATED (FY 2024–2025)
A17: Metric | B17: Jan | C17: Feb | D17: Mar | E17: Apr | F17: May | G17: Jun | H17: Jul | I17: Aug | J17: Sep | K17: Oct | L17: Nov | M17: Dec | N17: FY Total
A18: Revenue | B18: ='Monthly P&L'!B4 -> 46700 | C18: ='Monthly P&L'!C4 -> 43900 | D18: ='Monthly P&L'!D4 -> 52000 | E18: ='Monthly P&L'!E4 -> 65000 | F18: ='Monthly P&L'!F4 -> 81000 | G18: ='Monthly P&L'!G4 -> 91000 | H18: ='Monthly P&L'!H4 -> 101000 | I18: ='Monthly P&L'!I4 -> 97000 | ... N18: ='Monthly P&L'!N4 -> 805900
A19: COGS | B19: ='Monthly P&L'!B7 -> -15411 | C19: ='Monthly P&L'!C7 -> -14926 | D19: ='Monthly P&L'!D7 -> -17160 | E19: ='Monthly P&L'!E7 -> -20800 | F19: ='Monthly P&L'!F7 -> -25110 | G19: ='Monthly P&L'!G7 -> -27300 | H19: ='Monthly P&L'!H7 -> -29290 | I19: ='Monthly P&L'!I7 -> -29100 | ... N19: ='Monthly P&L'!N7 -> -253928
A20: Gross Profit | B20: ='Monthly P&L'!B8 -> 31289 | C20: ='Monthly P&L'!C8 -> 28974 | D20: ='Monthly P&L'!D8 -> 34840 | E20: ='Monthly P&L'!E8 -> 44200 | F20: ='Monthly P&L'!F8 -> 55890 | G20: ='Monthly P&L'!G8 -> 63700 | H20: ='Monthly P&L'!H8 -> 71710 | I20: ='Monthly P&L'!I8 -> 67900 | ... N20: ='Monthly P&L'!N8 -> 551972
A21: Gross Margin % | B21: ='Monthly P&L'!B10 -> 0.67 | C21: ='Monthly P&L'!C10 -> 0.66 | D21: ='Monthly P&L'!D10 -> 0.67 | E21: ='Monthly P&L'!E10 -> 0.68 | F21: ='Monthly P&L'!F10 -> 0.69 | G21: ='Monthly P&L'!G10 -> 0.7 | H21: ='Monthly P&L'!H10 -> 0.71 | I21: ='Monthly P&L'!I10 -> 0.7 | ... N21: ='Monthly P&L'!N10 -> 0.68491376

Sheet Monthly P&L
A1: CONSOLIDATED MONTHLY PROFIT & LOSS STATEMENT — FY 2024-2025
A2: Line Item | B2: Jan-25 | C2: Feb-25 | D2: Mar-25 | E2: Apr-25 | F2: May-25 | G2: Jun-25 | H2: Jul-25 | I2: Aug-25 | J2: Sep-25 | K2: Oct-25 | L2: Nov-25 | M2: Dec-25 | N2: FY Total
A3: REVENUE
A4: Total Revenue | B4: =B5+B6 -> 46700 | C4: =C5+C6 -> 43900 | D4: =D5+D6 -> 52000 | E4: =E5+E6 -> 65000 | F4: =F5+F6 -> 81000 | G4: =G5+G6 -> 91000 | H4: =H5+H6 -> 101000 | I4: =I5+I6 -> 97000 | ... M4: =M5+M6 -> 45600 | N4: =SUM(B4:M4) -> 805900
A5: Oakville Location | B5: 28500 | C5: 26800 | D5: 31200 | E5: 38500 | F5: 47200 | G5: 52800 | H5: 58500 | I5: 56200 | J5: 42800 | K5: 35600 | L5: 29800 | M5: 27500 | N5: =SUM(B5:M5) -> 475400
A6: High Park (Bloor) Location | B6: 18200 | C6: 17100 | D6: 20800 | E6: 26500 | F6: 33800 | G6: 38200 | H6: 42500 | I6: 40800 | J6: 30200 | K6: 24500 | L6: 19800 | M6: 18100 | N6: =SUM(B6:M6) -> 330500
A7: Cost of Goods Sold (COGS) | B7: =-B4*B30 -> -15411 | C7: =-C4*C30 -> -14926 | D7: =-D4*D30 -> -17160 | E7: =-E4*E30 -> -20800 | F7: =-F4*F30 -> -25110 | G7: =-G4*G30 -> -27300 | H7: =-H4*H30 -> -29290 | I7: =-I4*I30 -> -29100 | ... M7: =-M4*M30 -> -15504 | N7: =SUM(B7:M7) -> -253928
A8: Gross Profit | B8: =B4+B7 -> 31289 | C8: =C4+C7 -> 28974 | D8: =D4+D7 -> 34840 | E8: =E4+E7 -> 44200 | F8: =F4+F7 -> 55890 | G8: =G4+G7 -> 63700 | H8: =H4+H7 -> 71710 | I8: =I4+I7 -> 67900 | ... N8: =N4+N7 -> 551972
A10: Gross Margin % | B10: =IF(B4=0,0,B8/B4) -> 0.67 | C10: =IF(C4=0,0,C8/C4) -> 0.66 | D10: =IF(D4=0,0,D8/D4) -> 0.67 | E10: =IF(E4=0,0,E8/E4) -> 0.68 | F10: =IF(F4=0,0,F8/F4) -> 0.69 | G10: =IF(G4=0,0,G8/G4) -> 0.7 | H10: =IF(H4=0,0,H8/H4) -> 0.71 | I10: =IF(I4=0,0,I8/I4) -> 0.7 | ... N10: =IF(N4=0,0,N8/N4) -> 0.68491376
A11: OPERATING EXPENSES
A12: Rent (Both Locations) | B12: 9300 | C12: 9300 | D12: 9300 | E12: 9300 | F12: 9300 | G12: 9300 | H12: 9300 | I12: 9300 | J12: 9300 | K12: 9300 | L12: 9300 | M12: 9300 | N12: =SUM(B12:M12) -> 111600
A13: Labor & Staffing | B13: =B4*B31 -> 13076 | C13: =C4*C31 -> 12731 | D13: =D4*D31 -> 14040 | E13: =E4*E31 -> 16250 | F13: =F4*F31 -> 18630 | G13: =G4*G31 -> 20020 | H13: =H4*H31 -> 21210 | I13: =I4*I31 -> 21340 | ... M13: =M4*M31 -> 13224 | N13: =SUM(B13:M13) -> 197555
A14: Marketing & Promotions | B14: 800 | C14: 600 | D14: 1200 | E14: 1500 | F14: 2000 | G14: 2200 | H14: 2400 | I14: 2000 | J14: 1500 | K14: 1000 | L14: 800 | M14: 600 | N14: =SUM(B14:M14) -> 16600
A15: Total Operating Expenses | B15: =-(B12+B13+B14) -> -23176 | C15: =-(C12+C13+C14) -> -22631 | D15: =-(D12+D13+D14) -> -24540 | E15: =-(E12+E13+E14) -> -27050 | F15: =-(F12+F13+F14) -> -29930 | G15: =-(G12+G13+G14) -> -31520 | H15: =-(H12+H13+H14) -> -32910 | I15: =-(I12+I13+I14) -> -32640 | ... M15: =-(M12+M13+M14) -> -23124 | N15: =SUM(B15:M15) -> -325755
A17: EBITDA | B17: =B8+B15 -> 8113 | C17: =C8+C15 -> 6343 | D17: =D8+D15 -> 10300 | E17: =E8+E15 -> 17150 | F17: =F8+F15 -> 25960 | G17: =G8+G15 -> 32180 | H17: =H8+H15 -> 38800 | I17: =I8+I15 -> 35260 | ... N17: =N8+N15 -> 226217
A18: Net Income | B18: =B17 -> 8113 | C18: =C17 -> 6343 | D18: =D17 -> 10300 | E18: =E17 -> 17150 | F18: =F17 -> 25960 | G18: =G17 -> 32180 | H18: =H17 -> 38800 | I18: =I17 -> 35260 | ... N18: =N17 -> 226217
A19: Net Margin % | B19: =IF(B4=0,0,B18/B4) -> 0.17372591 | C19: =IF(C4=0,0,C18/C4) -> 0.14448747 | D19: =IF(D4=0,0,D18/D4) -> 0.19807692 | E19: =IF(E4=0,0,E18/E4) -> 0.26384615 | F19: =IF(F4=0,0,F18/F4) -> 0.32049383 | G19: =IF(G4=0,0,G18/G4) -> 0.35362637 | H19: =IF(H4=0,0,H18/H4) -> 0.38415842 | I19: =IF(I4=0,0,I18/I4) -> 0.36350515 | ... N19: =IF(N4=0,0,N18/N4) -> 0.28070108
A21: MoM Revenue Growth | B21: — | C21: =IF(B4=0,0,(C4-B4)/B4) -> -0.059957173 | D21: =IF(C4=0,0,(D4-C4)/C4) -> 0.18451025 | E21: =IF(D4=0,0,(E4-D4)/D4) -> 0.25 | F21: =IF(E4=0,0,(F4-E4)/E4) -> 0.24615385 | G21: =IF(F4=0,0,(G4-F4)/F4) -> 0.12345679 | H21: =IF(G4=0,0,(H4-G4)/G4) -> 0.10989011 | I21: =IF(H4=0,0,(I4-H4)/H4) -> -0.03960396 | J21: =IF(I4=0,0,(J4-I4)/I4) -> -0.24742268 | ... M21: =IF(L4=0,0,(M4-L4)/L4) -> -0.080645161
A22: Oakville % of Revenue | B22: =IF(B4=0,0,B5/B4) -> 0.61027837 | C22: =IF(C4=0,0,C5/C4) -> 0.61047836 | D22: =IF(D4=0,0,D5/D4) -> 0.6 | E22: =IF(E4=0,0,E5/E4) -> 0.59230769 | F22: =IF(F4=0,0,F5/F4) -> 0.58271605 | G22: =IF(G4=0,0,G5/G4) -> 0.58021978 | H22: =IF(H4=0,0,H5/H4) -> 0.57920792 | I22: =IF(I4=0,0,I5/I4) -> 0.57938144 | ... M22: =IF(M4=0,0,M5/M4) -> 0.60307018
A23: High Park % of Revenue | B23: =IF(B4=0,0,B6/B4) -> 0.38972163 | C23: =IF(C4=0,0,C6/C4) -> 0.38952164 | D23: =IF(D4=0,0,D6/D4) -> 0.4 | E23: =IF(E4=0,0,E6/E4) -> 0.40769231 | F23: =IF(F4=0,0,F6/F4) -> 0.41728395 | G23: =IF(G4=0,0,G6/G4) -> 0.41978022 | H23: =IF(H4=0,0,H6/H4) -> 0.42079208 | I23: =IF(I4=0,0,I6/I4) -> 0.42061856 | ... M23: =IF(M4=0,0,M6/M4) -> 0.39692982
A25: KEY ASSUMPTIONS (Blue = Input)
A26: Assumption | B26: Jan-25 | C26: Feb-25 | D26: Mar-25 | E26: Apr-25 | F26: May-25 | G26: Jun-25 | H26: Jul-25 | I26: Aug-25 | J26: Sep-25 | K26: Oct-25 | L26: Nov-25 | M26: Dec-25
A30: COGS % of Revenue | B30: 0.33 | C30: 0.34 | D30: 0.33 | E30: 0.32 | F30: 0.31 | G30: 0.3 | H30: 0.29 | I30: 0.3 | J30: 0.31 | K30: 0.33 | L30: 0.34 | M30: 0.34
A31: Labor % of Revenue | B31: 0.28 | C31: 0.29 | D31: 0.27 | E31: 0.25 | F31: 0.23 | G31: 0.22 | H31: 0.21 | I31: 0.22 | J31: 0.24 | K31: 0.26 | L31: 0.28 | M31: 0.29

Sheet Cash Flow
A1: CASH FLOW FORECAST — FY 2024-2025
A2: Line Item | B2: Jan-25 | C2: Feb-25 | D2: Mar-25 | E2: Apr-25 | F2: May-25 | G2: Jun-25 | H2: Jul-25 | I2: Aug-25 | J2: Sep-25 | K2: Oct-25 | L2: Nov-25 | M2: Dec-25 | N2: FY Total
A3: Opening Cash Balance | B3: 42000 | C3: =B19 -> 50113 | D3: =C19 -> 56456 | E3: =D19 -> 64756 | F3: =E19 -> 81906 | G3: =F19 -> 107866 | H3: =G19 -> 137046 | I3: =H19 -> 176646 | J3: =I19 -> 211906 | ... M3: =L19 -> 255545
A5: CASH INFLOWS
A6: Revenue Collected | B6: ='Monthly P&L'!B4 -> 46700 | C6: ='Monthly P&L'!C4 -> 43900 | D6: ='Monthly P&L'!D4 -> 52000 | E6: ='Monthly P&L'!E4 -> 65000 | F6: ='Monthly P&L'!F4 -> 81000 | G6: ='Monthly P&L'!G4 -> 91000 | H6: ='Monthly P&L'!H4 -> 101000 | I6: ='Monthly P&L'!I4 -> 97000 | ... M6: ='Monthly P&L'!M4 -> 45600 | N6: =SUM(B6:M6) -> 805900
A7: Other Income | B7: 0 | C7: 0 | D7: 500 | E7: 0 | F7: 0 | G7: 0 | H7: 800 | I7: 0 | J7: 0 | K7: 0 | L7: 0 | M7: 500 | N7: =SUM(B7:M7) -> 1800
A8: Total Cash Inflows | B8: =B6+B7 -> 46700 | C8: =C6+C7 -> 43900 | D8: =D6+D7 -> 52500 | E8: =E6+E7 -> 65000 | F8: =F6+F7 -> 81000 | G8: =G6+G7 -> 91000 | H8: =H6+H7 -> 101800 | I8: =I6+I7 -> 97000 | ... N8: =N6+N7 -> 807700
A10: CASH OUTFLOWS
A11: COGS Payments | B11: ='Monthly P&L'!B7 -> -15411 | C11: ='Monthly P&L'!C7 -> -14926 | D11: ='Monthly P&L'!D7 -> -17160 | E11: ='Monthly P&L'!E7 -> -20800 | F11: ='Monthly P&L'!F7 -> -25110 | G11: ='Monthly P&L'!G7 -> -27300 | H11: ='Monthly P&L'!H7 -> -29290 | I11: ='Monthly P&L'!I7 -> -29100 | ... M11: ='Monthly P&L'!M7 -> -15504 | N11: =SUM(B11:M11) -> -253928
A12: Rent Payments | B12: =-'Monthly P&L'!B12 -> -9300 | C12: =-'Monthly P&L'!C12 -> -9300 | D12: =-'Monthly P&L'!D12 -> -9300 | E12: =-'Monthly P&L'!E12 -> -9300 | F12: =-'Monthly P&L'!F12 -> -9300 | G12: =-'Monthly P&L'!G12 -> -9300 | H12: =-'Monthly P&L'!H12 -> -9300 | I12: =-'Monthly P&L'!I12 -> -9300 | ... M12: =-'Monthly P&L'!M12 -> -9300 | N12: =SUM(B12:M12) -> -111600
A13: Labor Payments | B13: =-'Monthly P&L'!B13 -> -13076 | C13: =-'Monthly P&L'!C13 -> -12731 | D13: =-'Monthly P&L'!D13 -> -14040 | E13: =-'Monthly P&L'!E13 -> -16250 | F13: =-'Monthly P&L'!F13 -> -18630 | G13: =-'Monthly P&L'!G13 -> -20020 | H13: =-'Monthly P&L'!H13 -> -21210 | I13: =-'Monthly P&L'!I13 -> -21340 | ... M13: =-'Monthly P&L'!M13 -> -13224 | N13: =SUM(B13:M13) -> -197555
A14: Marketing Spend | B14: =-'Monthly P&L'!B14 -> -800 | C14: =-'Monthly P&L'!C14 -> -600 | D14: =-'Monthly P&L'!D14 -> -1200 | E14: =-'Monthly P&L'!E14 -> -1500 | F14: =-'Monthly P&L'!F14 -> -2000 | G14: =-'Monthly P&L'!G14 -> -2200 | H14: =-'Monthly P&L'!H14 -> -2400 | I14: =-'Monthly P&L'!I14 -> -2000 | ... M14: =-'Monthly P&L'!M14 -> -600 | N14: =SUM(B14:M14) -> -16600
A15: Capital Expenditures | B15: 0 | C15: 0 | D15: -2500 | E15: 0 | F15: 0 | G15: -3000 | H15: 0 | I15: 0 | J15: -1500 | K15: 0 | L15: 0 | M15: 0 | N15: =SUM(B15:M15) -> -7000
A16: Total Cash Outflows | B16: =B11+B12+B13+B14+B15 -> -38587 | C16: =C11+C12+C13+C14+C15 -> -37557 | D16: =D11+D12+D13+D14+D15 -> -44200 | E16: =E11+E12+E13+E14+E15 -> -47850 | F16: =F11+F12+F13+F14+F15 -> -55040 | G16: =G11+G12+G13+G14+G15 -> -61820 | H16: =H11+H12+H13+H14+H15 -> -62200 | I16: =I11+I12+I13+I14+I15 -> -61740 | ... N16: =N11+N12+N13+N14+N15 -> -586683
A18: Net Cash Flow | B18: =B8+B16 -> 8113 | C18: =C8+C16 -> 6343 | D18: =D8+D16 -> 8300 | E18: =E8+E16 -> 17150 | F18: =F8+F16 -> 25960 | G18: =G8+G16 -> 29180 | H18: =H8+H16 -> 39600 | I18: =I8+I16 -> 35260 | ... N18: =N8+N16 -> 221017
A19: Closing Cash Balance | B19: =B3+B18 -> 50113 | C19: =C3+C18 -> 56456 | D19: =D3+D18 -> 64756 | E19: =E3+E18 -> 81906 | F19: =F3+F18 -> 107866 | G19: =G3+G18 -> 137046 | H19: =H3+H18 -> 176646 | I19: =I3+I18 -> 211906 | ... M19: =M3+M18 -> 263017 | N19: =M19 -> 263017

Sheet Margin Sensitivity
A1: MARGIN SENSITIVITY ANALYSIS
A2: How does net margin change with different COGS % and Labor % assumptions?
A4: BASE CASE INPUTS
A5: Annual Revenue | B5: ='Monthly P&L'!N4 -> 805900
A6: Base COGS % | B6: 0.315
A7: Base Labor % | B7: 0.25
A8: Fixed Costs (Rent + Mktg) | B8: ='Monthly P&L'!N12+'Monthly P&L'!N14 -> 128200
A9: Base Net Margin | B9: =1-B6-B7-B8/B5 -> 0.27592319
A11: NET MARGIN SENSITIVITY TABLE
A12: COGS % ↓ | B12: Labor % → | C12: 0.2 | D12: 0.22 | E12: 0.24 | F12: 0.25 | G12: 0.26 | H12: 0.28 | I12: 0.3
A13: 0.26 | C13: =1-$A13-C$12-$B$8/$B$5 -> 0.38092319 | D13: =1-$A13-D$12-$B$8/$B$5 -> 0.36092319 | E13: =1-$A13-E$12-$B$8/$B$5 -> 0.34092319 | F13: =1-$A13-F$12-$B$8/$B$5 -> 0.33092319 | G13: =1-$A13-G$12-$B$8/$B$5 -> 0.32092319 | H13: =1-$A13-H$12-$B$8/$B$5 -> 0.30092319 | I13: =1-$A13-I$12-$B$8/$B$5 -> 0.28092319
A14: 0.28 | C14: =1-$A14-C$12-$B$8/$B$5 -> 0.36092319 | D14: =1-$A14-D$12-$B$8/$B$5 -> 0.34092319 | E14: =1-$A14-E$12-$B$8/$B$5 -> 0.32092319 | F14: =1-$A14-F$12-$B$8/$B$5 -> 0.31092319 | G14: =1-$A14-G$12-$B$8/$B$5 -> 0.30092319 | H14: =1-$A14-H$12-$B$8/$B$5 -> 0.28092319 | I14: =1-$A14-I$12-$B$8/$B$5 -> 0.26092319
A15: 0.3 | C15: =1-$A15-C$12-$B$8/$B$5 -> 0.34092319 | D15: =1-$A15-D$12-$B$8/$B$5 -> 0.32092319 | E15: =1-$A15-E$12-$B$8/$B$5 -> 0.30092319 | F15: =1-$A15-F$12-$B$8/$B$5 -> 0.29092319 | G15: =1-$A15-G$12-$B$8/$B$5 -> 0.28092319 | H15: =1-$A15-H$12-$B$8/$B$5 -> 0.26092319 | I15: =1-$A15-I$12-$B$8/$B$5 -> 0.24092319
A16: 0.315 | C16: =1-$A16-C$12-$B$8/$B$5 -> 0.32592319 | D16: =1-$A16-D$12-$B$8/$B$5 -> 0.30592319 | E16: =1-$A16-E$12-$B$8/$B$5 -> 0.28592319 | F16: =1-$A16-F$12-$B$8/$B$5 -> 0.27592319 | G16: =1-$A16-G$12-$B$8/$B$5 -> 0.26592319 | H16: =1-$A16-H$12-$B$8/$B$5 -> 0.24592319 | I16: =1-$A16-I$12-$B$8/$B$5 -> 0.22592319
A17: 0.33 | C17: =1-$A17-C$12-$B$8/$B$5 -> 0.31092319 | D17: =1-$A17-D$12-$B$8/$B$5 -> 0.29092319 | E17: =1-$A17-E$12-$B$8/$B$5 -> 0.27092319 | F17: =1-$A17-F$12-$B$8/$B$5 -> 0.26092319 | G17: =1-$A17-G$12-$B$8/$B$5 -> 0.25092319 | H17: =1-$A17-H$12-$B$8/$B$5 -> 0.23092319 | I17: =1-$A17-I$12-$B$8/$B$5 -> 0.21092319
A18: 0.35 | C18: =1-$A18-C$12-$B$8/$B$5 -> 0.29092319 | D18: =1-$A18-D$12-$B$8/$B$5 -> 0.27092319 | E18: =1-$A18-E$12-$B$8/$B$5 -> 0.25092319 | F18: =1-$A18-F$12-$B$8/$B$5 -> 0.24092319 | G18: =1-$A18-G$12-$B$8/$B$5 -> 0.23092319 | H18: =1-$A18-H$12-$B$8/$B$5 -> 0.21092319 | I18: =1-$A18-I$12-$B$8/$B$5 -> 0.19092319
A19: 0.37 | C19: =1-$A19-C$12-$B$8/$B$5 -> 0.27092319 | D19: =1-$A19-D$12-$B$8/$B$5 -> 0.25092319 | E19: =1-$A19-E$12-$B$8/$B$5 -> 0.23092319 | F19: =1-$A19-F$12-$B$8/$B$5 -> 0.22092319 | G19: =1-$A19-G$12-$B$8/$B$5 -> 0.21092319 | H19: =1-$A19-H$12-$B$8/$B$5 -> 0.19092319 | I19: =1-$A19-I$12-$B$8/$B$5 -> 0.17092319
A20: 0.4 | C20: =1-$A20-C$12-$B$8/$B$5 -> 0.24092319 | D20: =1-$A20-D$12-$B$8/$B$5 -> 0.22092319 | E20: =1-$A20-E$12-$B$8/$B$5 -> 0.20092319 | F20: =1-$A20-F$12-$B$8/$B$5 -> 0.19092319 | G20: =1-$A20-G$12-$B$8/$B$5 -> 0.18092319 | H20: =1-$A20-H$12-$B$8/$B$5 -> 0.16092319 | I20: =1-$A20-I$12-$B$8/$B$5 -> 0.14092319
A23: REVENUE SCENARIO ANALYSIS
A24: Scenario | B24: Growth | C24: Projected Revenue | D24: Gross Profit | E24: Net Income | F24: Net Margin
A25: Bear Case (-15%) | B25: -0.15 | C25: =$B$5*(1+B25) -> 685015 | D25: =C25*(1-$B$6) -> 469235.28 | E25: =C25*(1-$B$6-$B$7)-$B$8 -> 169781.53 | F25: =IF(C25=0,0,E25/C25) -> 0.24785081
A26: Moderate Decline (-8%) | B26: -0.08 | C26: =$B$5*(1+B26) -> 741428 | D26: =C26*(1-$B$6) -> 507878.18 | E26: =C26*(1-$B$6-$B$7)-$B$8 -> 194321.18 | F26: =IF(C26=0,0,E26/C26) -> 0.26209043
A27: Base Case | B27: 0 | C27: =$B$5*(1+B27) -> 805900 | D27: =C27*(1-$B$6) -> 552041.5 | E27: =C27*(1-$B$6-$B$7)-$B$8 -> 222366.5 | F27: =IF(C27=0,0,E27/C27) -> 0.27592319
A28: Moderate Growth (+8%) | B28: 0.08 | C28: =$B$5*(1+B28) -> 870372 | D28: =C28*(1-$B$6) -> 596204.82 | E28: =C28*(1-$B$6-$B$7)-$B$8 -> 250411.82 | F28: =IF(C28=0,0,E28/C28) -> 0.28770666
A29: Bull Case (+15%) | B29: 0.15 | C29: =$B$5*(1+B29) -> 926785 | D29: =C29*(1-$B$6) -> 634847.72 | E29: =C29*(1-$B$6-$B$7)-$B$8 -> 274951.47 | F29: =IF(C29=0,0,E29/C29) -> 0.29667234

Sheet KPI Tracker
A1: OPERATIONAL KPI TRACKER — FY 2024-2025
A2: KPI | B2: Jan-25 | C2: Feb-25 | D2: Mar-25 | E2: Apr-25 | F2: May-25 | G2: Jun-25 | H2: Jul-25 | I2: Aug-25 | J2: Sep-25 | K2: Oct-25 | L2: Nov-25 | M2: Dec-25 | N2: FY Avg/Total
A3: SALES KPIs
A4: Total Revenue | B4: ='Monthly P&L'!B4 -> 46700 | C4: ='Monthly P&L'!C4 -> 43900 | D4: ='Monthly P&L'!D4 -> 52000 | E4: ='Monthly P&L'!E4 -> 65000 | F4: ='Monthly P&L'!F4 -> 81000 | G4: ='Monthly P&L'!G4 -> 91000 | H4: ='Monthly P&L'!H4 -> 101000 | I4: ='Monthly P&L'!I4 -> 97000 | ... M4: ='Monthly P&L'!M4 -> 45600 | N4: =SUM(B4:M4) -> 805900
A5: Total Transactions | B5: 4680 | C5: 4390 | D5: 5200 | E5: 6500 | F5: 8100 | G5: 9100 | H5: 10100 | I5: 9700 | J5: 7300 | K5: 6010 | L5: 4960 | M5: 4560 | N5: =SUM(B5:M5) -> 80600
A6: Average Order Value (AOV) | B6: =IF(B5=0,0,B4/B5) -> 9.9786325 | C6: =IF(C5=0,0,C4/C5) -> 10 | D6: =IF(D5=0,0,D4/D5) -> 10 | E6: =IF(E5=0,0,E4/E5) -> 10 | F6: =IF(F5=0,0,F4/F5) -> 10 | G6: =IF(G5=0,0,G4/G5) -> 10 | H6: =IF(H5=0,0,H4/H5) -> 10 | I6: =IF(I5=0,0,I4/I5) -> 10 | ... N6: =IF(N5=0,0,N4/N5) -> 9.9987593
A7: Revenue per Location | B7: =B4/2 -> 23350 | C7: =C4/2 -> 21950 | D7: =D4/2 -> 26000 | E7: =E4/2 -> 32500 | F7: =F4/2 -> 40500 | G7: =G4/2 -> 45500 | H7: =H4/2 -> 50500 | I7: =I4/2 -> 48500 | ... N7: =N4/2 -> 402950
A9: PROFITABILITY KPIs
A10: Gross Margin % | B10: ='Monthly P&L'!B10 -> 0.67 | C10: ='Monthly P&L'!C10 -> 0.66 | D10: ='Monthly P&L'!D10 -> 0.67 | E10: ='Monthly P&L'!E10 -> 0.68 | F10: ='Monthly P&L'!F10 -> 0.69 | G10: ='Monthly P&L'!G10 -> 0.7 | H10: ='Monthly P&L'!H10 -> 0.71 | I10: ='Monthly P&L'!I10 -> 0.7 | ... M10: ='Monthly P&L'!M10 -> 0.66 | N10: =AVERAGE(B10:M10) -> 0.68
A11: Net Margin % | B11: ='Monthly P&L'!B19 -> 0.17372591 | C11: ='Monthly P&L'!C19 -> 0.14448747 | D11: ='Monthly P&L'!D19 -> 0.19807692 | E11: ='Monthly P&L'!E19 -> 0.26384615 | F11: ='Monthly P&L'!F19 -> 0.32049383 | G11: ='Monthly P&L'!G19 -> 0.35362637 | H11: ='Monthly P&L'!H19 -> 0.38415842 | I11: ='Monthly P&L'!I19 -> 0.36350515 | ... M11: ='Monthly P&L'!M19 -> 0.15289474 | N11: =AVERAGE(B11:M11) -> 0.25598831
A12: COGS % of Revenue | B12: ='Monthly P&L'!B30 -> 0.33 | C12: ='Monthly P&L'!C30 -> 0.34 | D12: ='Monthly P&L'!D30 -> 0.33 | E12: ='Monthly P&L'!E30 -> 0.32 | F12: ='Monthly P&L'!F30 -> 0.31 | G12: ='Monthly P&L'!G30 -> 0.3 | H12: ='Monthly P&L'!H30 -> 0.29 | I12: ='Monthly P&L'!I30 -> 0.3 | ... M12: ='Monthly P&L'!M30 -> 0.34 | N12: =AVERAGE(B12:M12) -> 0.32
A13: Labor % of Revenue | B13: ='Monthly P&L'!B31 -> 0.28 | C13: ='Monthly P&L'!C31 -> 0.29 | D13: ='Monthly P&L'!D31 -> 0.27 | E13: ='Monthly P&L'!E31 -> 0.25 | F13: ='Monthly P&L'!F31 -> 0.23 | G13: ='Monthly P&L'!G31 -> 0.22 | H13: ='Monthly P&L'!H31 -> 0.21 | I13: ='Monthly P&L'!I31 -> 0.22 | ... M13: ='Monthly P&L'!M31 -> 0.29 | N13: =AVERAGE(B13:M13) -> 0.25333333
A15: EFFICIENCY KPIs
A16: Revenue per Staff Member | B16: =B4/B17 -> 7783.3333 | C16: =C4/C17 -> 7316.6667 | D16: =D4/D17 -> 7428.5714 | E16: =E4/E17 -> 8125 | F16: =F4/F17 -> 8100 | G16: =G4/G17 -> 7583.3333 | H16: =H4/H17 -> 8416.6667 | I16: =I4/I17 -> 8818.1818 | ... M16: =M4/M17 -> 7600
A17: Staff Count | B17: 6 | C17: 6 | D17: 7 | E17: 8 | F17: 10 | G17: 12 | H17: 12 | I17: 11 | J17: 9 | K17: 8 | L17: 7 | M17: 6 | N17: =MAX(B17:M17) -> 12
A18: Inventory Turnover (est.) | B18: 8.2 | C18: 7.9 | D18: 8.5 | E18: 9.1 | F18: 10.2 | G18: 11 | H18: 11.5 | I18: 10.8 | J18: 9.5 | K18: 8.8 | L18: 8.1 | M18: 7.8 | N18: =AVERAGE(B18:M18) -> 9.2833333
A20: GROWTH KPIs
A21: MoM Revenue Growth | B21: — | C21: ='Monthly P&L'!C21 -> -0.059957173 | D21: ='Monthly P&L'!D21 -> 0.18451025 | E21: ='Monthly P&L'!E21 -> 0.25 | F21: ='Monthly P&L'!F21 -> 0.24615385 | G21: ='Monthly P&L'!G21 -> 0.12345679 | H21: ='Monthly P&L'!H21 -> 0.10989011 | I21: ='Monthly P&L'!I21 -> -0.03960396 | J21: ='Monthly P&L'!J21 -> -0.24742268 | ... M21: ='Monthly P&L'!M21 -> -0.080645161 | N21: =AVERAGE(C21:M21) -> 0.01226917
A22: Cumulative Revenue | B22: =B4 -> 46700 | C22: =B22+C4 -> 90600 | D22: =C22+D4 -> 142600 | E22: =D22+E4 -> 207600 | F22: =E22+F4 -> 288600 | G22: =F22+G4 -> 379600 | H22: =G22+H4 -> 480600 | I22: =H22+I4 -> 577600 | J22: =I22+J4 -> 650600 | ... M22: =L22+M4 -> 805900 | N22: =M22 -> 805900

Sheet Variance Analysis
A1: BUDGET vs. ACTUAL VARIANCE ANALYSIS — FY 2024-2025
A2: Line Item | B2: Annual Budget | C2: Annual Actual | D2: Variance ($) | E2: Variance (%) | F2: Status | G2: Alert Level | H2: Action Required
A3: Total Revenue | B3: 565000 | C3: ='Monthly P&L'!N4 -> 805900 | D3: =C3-B3 -> 240900 | E3: =IF(B3=0,0,D3/ABS(B3)) -> 0.42637168 | F3: =IF(E3>0.02,"Favorable",IF(E3<-0.02,"Unfavorable","On Track")) -> Favorable | G3: =IF(ABS(E3)>0.1,"HIGH",IF(ABS(E3)>0.05,"MEDIUM","LOW")) -> HIGH | H3: =IF(ABS(E3)>0.05,"Review & adjust forecast","Monitor") -> Review & adjust forecast
A4: Oakville Revenue | B4: 330000 | C4: ='Monthly P&L'!N5 -> 475400 | D4: =C4-B4 -> 145400 | E4: =IF(B4=0,0,D4/ABS(B4)) -> 0.44060606 | F4: =IF(E4>0.02,"Favorable",IF(E4<-0.02,"Unfavorable","On Track")) -> Favorable | G4: =IF(ABS(E4)>0.1,"HIGH",IF(ABS(E4)>0.05,"MEDIUM","LOW")) -> HIGH | H4: =IF(ABS(E4)>0.05,"Review & adjust forecast","Monitor") -> Review & adjust forecast
A5: High Park Revenue | B5: 235000 | C5: ='Monthly P&L'!N6 -> 330500 | D5: =C5-B5 -> 95500 | E5: =IF(B5=0,0,D5/ABS(B5)) -> 0.40638298 | F5: =IF(E5>0.02,"Favorable",IF(E5<-0.02,"Unfavorable","On Track")) -> Favorable | G5: =IF(ABS(E5)>0.1,"HIGH",IF(ABS(E5)>0.05,"MEDIUM","LOW")) -> HIGH | H5: =IF(ABS(E5)>0.05,"Review & adjust forecast","Monitor") -> Review & adjust forecast
A6: COGS | B6: -178000 | C6: ='Monthly P&L'!N7 -> -253928 | D6: =C6-B6 -> -75928 | E6: =IF(B6=0,0,D6/ABS(B6)) -> -0.4265618 | F6: =IF(E6>0.02,"Favorable",IF(E6<-0.02,"Unfavorable","On Track")) -> Unfavorable | G6: =IF(ABS(E6)>0.1,"HIGH",IF(ABS(E6)>0.05,"MEDIUM","LOW")) -> HIGH | H6: =IF(ABS(E6)>0.05,"Review & adjust forecast","Monitor") -> Review & adjust forecast
A7: Gross Profit | B7: 387000 | C7: ='Monthly P&L'!N8 -> 551972 | D7: =C7-B7 -> 164972 | E7: =IF(B7=0,0,D7/ABS(B7)) -> 0.42628424 | F7: =IF(E7>0.02,"Favorable",IF(E7<-0.02,"Unfavorable","On Track")) -> Favorable | G7: =IF(ABS(E7)>0.1,"HIGH",IF(ABS(E7)>0.05,"MEDIUM","LOW")) -> HIGH | H7: =IF(ABS(E7)>0.05,"Review & adjust forecast","Monitor") -> Review & adjust forecast
A8: Rent | B8: -111600 | C8: =-'Monthly P&L'!N12 -> -111600 | D8: =C8-B8 -> 0 | E8: =IF(B8=0,0,D8/ABS(B8)) -> 0 | F8: =IF(E8>0.02,"Favorable",IF(E8<-0.02,"Unfavorable","On Track")) -> On Track | G8: =IF(ABS(E8)>0.1,"HIGH",IF(ABS(E8)>0.05,"MEDIUM","LOW")) -> LOW | H8: =IF(ABS(E8)>0.05,"Review & adjust forecast","Monitor") -> Monitor
A9: Labor | B9: -141250 | C9: =-'Monthly P&L'!N13 -> -197555 | D9: =C9-B9 -> -56305 | E9: =IF(B9=0,0,D9/ABS(B9)) -> -0.39861947 | F9: =IF(E9>0.02,"Favorable",IF(E9<-0.02,"Unfavorable","On Track")) -> Unfavorable | G9: =IF(ABS(E9)>0.1,"HIGH",IF(ABS(E9)>0.05,"MEDIUM","LOW")) -> HIGH | H9: =IF(ABS(E9)>0.05,"Review & adjust forecast","Monitor") -> Review & adjust forecast
A10: Marketing | B10: -15000 | C10: =-'Monthly P&L'!N14 -> -16600 | D10: =C10-B10 -> -1600 | E10: =IF(B10=0,0,D10/ABS(B10)) -> -0.10666667 | F10: =IF(E10>0.02,"Favorable",IF(E10<-0.02,"Unfavorable","On Track")) -> Unfavorable | G10: =IF(ABS(E10)>0.1,"HIGH",IF(ABS(E10)>0.05,"MEDIUM","LOW")) -> HIGH | H10: =IF(ABS(E10)>0.05,"Review & adjust forecast","Monitor") -> Review & adjust forecast
A11: Total OpEx | B11: -267850 | C11: ='Monthly P&L'!N15 -> -325755 | D11: =C11-B11 -> -57905 | E11: =IF(B11=0,0,D11/ABS(B11)) -> -0.21618443 | F11: =IF(E11>0.02,"Favorable",IF(E11<-0.02,"Unfavorable","On Track")) -> Unfavorable | G11: =IF(ABS(E11)>0.1,"HIGH",IF(ABS(E11)>0.05,"MEDIUM","LOW")) -> HIGH | H11: =IF(ABS(E11)>0.05,"Review & adjust forecast","Monitor") -> Review & adjust forecast
A12: EBITDA | B12: 119150 | C12: ='Monthly P&L'!N17 -> 226217 | D12: =C12-B12 -> 107067 | E12: =IF(B12=0,0,D12/ABS(B12)) -> 0.89859001 | F12: =IF(E12>0.02,"Favorable",IF(E12<-0.02,"Unfavorable","On Track")) -> Favorable | G12: =IF(ABS(E12)>0.1,"HIGH",IF(ABS(E12)>0.05,"MEDIUM","LOW")) -> HIGH | H12: =IF(ABS(E12)>0.05,"Review & adjust forecast","Monitor") -> Review & adjust forecast
A13: Net Income | B13: 119150 | C13: ='Monthly P&L'!N18 -> 226217 | D13: =C13-B13 -> 107067 | E13: =IF(B13=0,0,D13/ABS(B13)) -> 0.89859001 | F13: =IF(E13>0.02,"Favorable",IF(E13<-0.02,"Unfavorable","On Track")) -> Favorable | G13: =IF(ABS(E13)>0.1,"HIGH",IF(ABS(E13)>0.05,"MEDIUM","LOW")) -> HIGH | H13: =IF(ABS(E13)>0.05,"Review & adjust forecast","Monitor") -> Review & adjust forecast

Sheet Notes & Methodology
A1: METHODOLOGY & DOCUMENTATION
A3: Model Overview | B3: AI-assisted financial reporting dashboard for La Diperie (two dessert retail locations). Built to simulate fund-style reporting for strategic decision-making across $550K+ revenue base.
A4: Data Source | B4: POS system exports (Square), manual inventory logs, bank statements, and payroll records. All figures represent realistic operating data for a dessert retail franchise.
A5: Revenue Model | B5: Revenue is tracked by location (Oakville and High Park/Bloor). Seasonal patterns reflect dessert retail cycles: peak June–August, trough December–February.
A6: COGS Assumptions | B6: COGS % varies monthly (29%–34%) reflecting seasonal ingredient cost fluctuations, supplier pricing tiers, and product mix changes. Blue-font inputs are adjustable.
A7: Labor Model | B7: Labor as % of revenue ranges from 21% (peak season efficiency) to 29% (off-season fixed staff costs). Staff count scales from 6 to 12 based on demand.
A8: Cash Flow | B8: Opening balance of $42,000. Cash inflows = revenue collected. Outflows include COGS, rent, labor, marketing, and periodic capital expenditures.
A9: Margin Sensitivity | B9: Two-variable data table testing COGS % (26%–40%) against Labor % (20%–30%) impact on net margin. Color-scaled for quick identification of risk zones.
A10: Variance Analysis | B10: Budget figures represent planned FY targets. Actual figures pull dynamically from the P&L sheet. Automated alerts flag variances exceeding ±5% for review.
A11: Color Convention | B11: Blue text = hardcoded input (adjustable). Black text = formula/calculation. Green = cross-sheet reference. Yellow highlight = key output.
A12: Prepared By | B12: Anis Bouchema — Business Technology Management Student, Toronto Metropolitan University. Contact: anis.bouchema@torontomu.ca
A13: Tools Used | B13: Microsoft Excel (advanced), POS Analytics (Square), AI-assisted forecasting logic.
A14: Version | B14: v1.0 — February 2025
